pyvzutil
