Metadata-Version: 1.1
Name: pyvzutil
Version: 0.0.10
Summary: Utilities for working with openvz clusters
Home-page: http://github.com/stroxler/pyvzutil
Author: Steven Troxler
Author-email: steven.troxler@gmail.com
License: MIT
Keywords: cluster ssh openvz scp
Platform: UNKNOWN
Classifier: Development Status :: 3 - Alpha
Classifier: License :: OSI Approved :: MIT License
Classifier: Programming Language :: Python :: 2.7
